odoo/addons/maintenance_equipment_category_hierarchy/README.rst
odoo/addons/maintenance_equipment_category_hierarchy/__init__.py
odoo/addons/maintenance_equipment_category_hierarchy/__manifest__.py
odoo/addons/maintenance_equipment_category_hierarchy/i18n/es.po
odoo/addons/maintenance_equipment_category_hierarchy/i18n/fr.po
odoo/addons/maintenance_equipment_category_hierarchy/i18n/it.po
odoo/addons/maintenance_equipment_category_hierarchy/i18n/maintenance_equipment_category_hierarchy.pot
odoo/addons/maintenance_equipment_category_hierarchy/models/__init__.py
odoo/addons/maintenance_equipment_category_hierarchy/models/maintenance_equipment_category.py
odoo/addons/maintenance_equipment_category_hierarchy/readme/CONTRIBUTORS.rst
odoo/addons/maintenance_equipment_category_hierarchy/readme/DESCRIPTION.rst
odoo/addons/maintenance_equipment_category_hierarchy/static/description/icon.png
odoo/addons/maintenance_equipment_category_hierarchy/static/description/index.html
odoo/addons/maintenance_equipment_category_hierarchy/tests/__init__.py
odoo/addons/maintenance_equipment_category_hierarchy/tests/test_maintenance_category.py
odoo/addons/maintenance_equipment_category_hierarchy/views/maintenance_equipment_category.xml
odoo14_addon_maintenance_equipment_category_hierarchy-14.0.1.0.1.dev7.dist-info/METADATA
odoo14_addon_maintenance_equipment_category_hierarchy-14.0.1.0.1.dev7.dist-info/WHEEL
odoo14_addon_maintenance_equipment_category_hierarchy-14.0.1.0.1.dev7.dist-info/top_level.txt
odoo14_addon_maintenance_equipment_category_hierarchy-14.0.1.0.1.dev7.dist-info/RECORD
